{"rows":[{"c":[{"v":"DE-BW","f":"Baden-Württemberg"},{"v":"2155"},{"v":"6"}]},{"c":[{"v":"DE-BY","f":"Bayern"},{"v":"1692"},{"v":"8"}]},{"c":[{"v":"DE-BE","f":"Berlin"},{"v":"573"},{"v":"0"}]},{"c":[{"v":"DE-BB","f":"Brandenburg"},{"v":"134"},{"v":"0"}]},{"c":[{"v":"DE-HB","f":"Bremen"},{"v":"80"},{"v":"0"}]},{"c":[{"v":"DE-HH","f":"Hamburg"},{"v":"432"},{"v":"0"}]},{"c":[{"v":"DE-HE","f":"Hessen"},{"v":"682"},{"v":"0"}]},{"c":[{"v":"DE-MV","f":"Mecklenburg-Vorpommern"},{"v":"98"},{"v":"0"}]},{"c":[{"v":"DE-NI","f":"Niedersachsen"},{"v":"669"},{"v":"0"}]},{"c":[{"v":"DE-NW","f":"Nordrhein-Westfalen"},{"v":"3033"},{"v":"6"}]},{"c":[{"v":"DE-RP","f":"Rheinland-Pfalz"},{"v":"637"},{"v":"0"}]},{"c":[{"v":"DE-SL","f":"Saarland"},{"v":"99"},{"v":"0"}]},{"c":[{"v":"DE-SN","f":"Sachsen"},{"v":"275"},{"v":"0"}]},{"c":[{"v":"DE-ST","f":"Sachsen-Anhalt"},{"v":"140"},{"v":"0"}]},{"c":[{"v":"DE-SH","f":"Schleswig-Holstein"},{"v":"202"},{"v":"0"}]},{"c":[{"v":"DE-TH","f":"Thüringen"},{"v":"98"},{"v":"0"}]}],"cols":[{"pattern":"","id":"","label":"Bundesland","type":"string"},{"pattern":"","id":"","label":"Bestätiger","type":"number"},{"pattern":"","id":"","label":"Tod","type":"number"}]}